Workbook

Sheet Read Me
A1: FundExecs Technologies — 5-Year Financial Model
A2: Confidential · July 2026
A4: This workbook is an illustrative planning model, not a forecast. All figures are
A5: management estimates derived from the assumptions on the 'Assumptions' sheet and
A6: should be stress-tested in diligence. FY1 begins at close of the seed round
A7: (assumed Q4 2026). Figures in USD.
A9: Sheets:
A10: Assumptions — pricing, mix, usage uplift, customers, churn, NRR, cost ratios
A11: Revenue Build — blended ARPA and ARR computed by formula from Assumptions
A12: P&L — recognized revenue, COGS, OpEx, EBITDA (formula-driven)
A13: Headcount — hiring plan by function
A14: Sensitivities — downside scenarios and mitigants
A16: Change any blue input cell on Assumptions and the model recalculates.

Sheet Assumptions
A1: Assumptions
A2: Blue cells are inputs — edit these; everything else is formula-driven.
B4: FY1 | C4: FY2 | D4: FY3 | E4: FY4 | F4: FY5
A5: Pricing ($/org/month)
A6: Starter-tier equivalent | B6: 50 | C6: 100 | D6: 125 | E6: 150 | F6: 175
A7: Pro-tier equivalent | B7: 300 | C7: 450 | D7: 600 | E7: 700 | F7: 800
A8: Scale-tier equivalent | B8: 1000 | C8: 1250 | D8: 1500 | E8: 1750 | F8: 2000
A9: Customer mix (must sum to 100%)
A10: Starter mix | B10: 0.55 | C10: 0.5 | D10: 0.45 | E10: 0.4 | F10: 0.35
A11: Pro mix | B11: 0.35 | C11: 0.38 | D11: 0.4 | E11: 0.42 | F11: 0.43
A12: Scale mix | B12: 0.1 | C12: 0.12 | D12: 0.15 | E12: 0.18 | F12: 0.22
A13: Usage & customers
A14: Credits/usage uplift on subscription | B14: 0.15 | C14: 0.2 | D14: 0.25 | E14: 0.3 | F14: 0.3
A15: Paying orgs (EOY) | B15: 40 | C15: 160 | D15: 450 | E15: 1000 | F15: 1900
A16: Gross logo churn (annual) | B16: 0.15 | C16: 0.15 | D16: 0.12 | E16: 0.1 | F16: 0.1
A17: Net revenue retention | B17: 1 | C17: 1.1 | D17: 1.15 | E17: 1.18 | F17: 1.2
A18: Other revenue & cost ratios
A19: Marketplace + data/API ARR ($M, EOY) | B19: 0 | C19: 0.05 | D19: 0.55 | E19: 1.5 | F19: 3
A20: COGS as % of revenue | B20: 0.55 | C20: 0.31 | D20: 0.23 | E20: 0.21 | F20: 0.19
A21: OpEx plan ($M)
A22: R&D / Engineering | B22: 0.9 | C22: 1.5 | D22: 2.6 | E22: 4.5 | F22: 7
A23: Sales & Marketing | B23: 0.2 | C23: 0.5 | D23: 1.3 | E23: 2.7 | F23: 4.9
A24: G&A (incl. legal/compliance) | B24: 0.3 | C24: 0.5 | D24: 0.9 | E24: 1.6 | F24: 2.5

Sheet Revenue Build
A1: Revenue Build
A2: Formula-driven from the Assumptions sheet.
B4: FY1 | C4: FY2 | D4: FY3 | E4: FY4 | F4: FY5
A5: Blended ARPA ($/org/yr) | B5: =(Assumptions!B6*Assumptions!B10+Assumptions!B7*Assumptions!B11+Assumptions!B8*Assumptions!B12)*12*(1+Assumptions!B14) | C5: =(Assumptions!C6*Assumptions!C10+Assumptions!C7*Assumptions!C11+Assumptions!C8*Assumptions!C12)*12*(1+Assumptions!C14) | D5: =(Assumptions!D6*Assumptions!D10+Assumptions!D7*Assumptions!D11+Assumptions!D8*Assumptions!D12)*12*(1+Assumptions!D14) | E5: =(Assumptions!E6*Assumptions!E10+Assumptions!E7*Assumptions!E11+Assumptions!E8*Assumptions!E12)*12*(1+Assumptions!E14) | F5: =(Assumptions!F6*Assumptions!F10+Assumptions!F7*Assumptions!F11+Assumptions!F8*Assumptions!F12)*12*(1+Assumptions!F14)
A6: Subscription + usage ARR ($M, EOY) | B6: =Assumptions!B15*B5/1000000 | C6: =Assumptions!C15*C5/1000000 | D6: =Assumptions!D15*D5/1000000 | E6: =Assumptions!E15*E5/1000000 | F6: =Assumptions!F15*F5/1000000
A7: Marketplace + data/API ARR ($M) | B7: =Assumptions!B19 | C7: =Assumptions!C19 | D7: =Assumptions!D19 | E7: =Assumptions!E19 | F7: =Assumptions!F19
A8: Total ARR ($M, EOY) | B8: =B6+B7 | C8: =C6+C7 | D8: =D6+D7 | E8: =E6+E7 | F8: =F6+F7
A9: Recognized revenue ($M) ≈ avg ARR × 95% | B9: =(0+B8)/2*0.95 | C9: =(B8+C8)/2*0.95 | D9: =(C8+D8)/2*0.95 | E9: =(D8+E8)/2*0.95 | F9: =(E8+F8)/2*0.95

Sheet P&L
A1: P&L Summary ($M)
A2: Formula-driven; EBITDA breakeven expected late FY5 on plan.
B4: FY1 | C4: FY2 | D4: FY3 | E4: FY4 | F4: FY5
A5: Revenue | B5: ='Revenue Build'!B9 | C5: ='Revenue Build'!C9 | D5: ='Revenue Build'!D9 | E5: ='Revenue Build'!E9 | F5: ='Revenue Build'!F9
A6: COGS (AI compute, infra, support) | B6: =B5*Assumptions!B20 | C6: =C5*Assumptions!C20 | D6: =D5*Assumptions!D20 | E6: =E5*Assumptions!E20 | F6: =F5*Assumptions!F20
A7: Gross profit | B7: =B5-B6 | C7: =C5-C6 | D7: =D5-D6 | E7: =E5-E6 | F7: =F5-F6
A8: Gross margin | B8: =IF(B5=0,0,B7/B5) | C8: =IF(C5=0,0,C7/C5) | D8: =IF(D5=0,0,D7/D5) | E8: =IF(E5=0,0,E7/E5) | F8: =IF(F5=0,0,F7/F5)
A9: R&D / Engineering | B9: =Assumptions!B22 | C9: =Assumptions!C22 | D9: =Assumptions!D22 | E9: =Assumptions!E22 | F9: =Assumptions!F22
A10: Sales & Marketing | B10: =Assumptions!B23 | C10: =Assumptions!C23 | D10: =Assumptions!D23 | E10: =Assumptions!E23 | F10: =Assumptions!F23
A11: G&A | B11: =Assumptions!B24 | C11: =Assumptions!C24 | D11: =Assumptions!D24 | E11: =Assumptions!E24 | F11: =Assumptions!F24
A12: Total OpEx | B12: =SUM(B9:B11) | C12: =SUM(C9:C11) | D12: =SUM(D9:D11) | E12: =SUM(E9:E11) | F12: =SUM(F9:F11)
A13: EBITDA | B13: =B7-B12 | C13: =C7-C12 | D13: =D7-D12 | E13: =E7-E12 | F13: =F7-F12

Sheet Headcount
A1: Headcount Plan (FTEs, EOY)
B4: FY1 | C4: FY2 | D4: FY3 | E4: FY4 | F4: FY5
A5: Engineering & product | B5: 4 | C5: 7 | D5: 12 | E5: 20 | F5: 30
A6: GTM & success | B6: 1 | C6: 3 | D6: 7 | E6: 13 | F6: 21
A7: G&A / ops | B7: 1 | C7: 2 | D7: 3 | E7: 5 | F7: 8
A8: Total | B8: =SUM(B5:B7) | C8: =SUM(C5:C7) | D8: =SUM(D5:D7) | E8: =SUM(E5:E7) | F8: =SUM(F5:F7)

Sheet Sensitivities
A1: Key Sensitivities
A4: Variable | B4: Downside effect | C4: Mitigant
A5: Repricing lags proof of value | B5: FY3+ ARR −40–50% | C5: Credits still capture usage growth; delay hires to match
A6: Churn 20%+ in beachhead | B6: FY5 orgs ~1,300 | C6: Compounding graphs/Brains raise switching costs with tenure
A7: AI compute cost doesn't fall | B7: Gross margin plateaus ~70% | C7: Cost-tiered routing (live), per-run caps, pass-through via credits
A8: Slower logo adds (half pace) | B8: FY5 ARR ~$14M | C8: Still a strong Series B profile; burn scales down with GTM spend
